{
  "metadata" : {
    "identifier" : "https://truyenvnmoi.com/tsundere-akuyaku-reijou-liselotte-to-jikkyou-no-endo-kun-to-kaisetsu-no-kobayashi-san",
    "title" : "Tsundere Akuyaku Reijou Liselotte To Jikkyou No Endo-Kun To Kaisetsu No Kobayashi-San",
    "subtitle" : null,
    "author" : null,
    "narrator" : null,
    "language" : "vi",
    "description" : null,
    "publisher" : "N/A",
    "subject" : null,
    "modified" : null,
    "published" : "2023-05-01",
    "duration" : 0,
    "abridged" : false,
    "conformsTo" : "https://readium.org/webpub-manifest/profiles/divina",
    "numberOfPages" : 34,
    "readingProgression" : "ttb",
    "belongsTo" : null,
    "presentation" : {
      "fit" : "width",
      "overflow" : "scrolled",
      "continuous" : true
    },
    "@type" : null,
    "schema:license" : null
  },
  "links" : [ {
    "rel" : "self",
    "href" : "https://raw.githubusercontent.com/thuvienonline40/book_storage_collection/main/comic_manifest.json",
    "type" : "application/divina+json"
  } ],
  "readingOrder" : [ {
    "href" : "https://bitbucket.org/wp-tsvhcomic11/comic_storage_two15/raw/master/IMAGE/IMAGE_b38a5f72f44377918adb1ed66534f764_a0092bb9390c00ed01ea830059fd4a97_ef094e3c4263b24bcbbb0eb698a89c0f.jpg",
    "type" : "image/jpeg",
    "bitrate" : 0,
    "duration" : 0,
    "title" : null,
    "properties" : null,
    "alternate" : [ {
      "href" : "https://img.abctruyen.xyz/uploads/9925/chuong-15/0.jpg",
      "type" : "image/jpeg",
      "bitrate" : 0,
      "duration" : 0,
      "title" : null,
      "properties" : null,
      "alternate" : null
    } ]
  }, {
    "href" : "https://bitbucket.org/wp-tsvhcomic11/comic_storage_two15/raw/master/IMAGE/IMAGE_b38a5f72f44377918adb1ed66534f764_a0092bb9390c00ed01ea830059fd4a97_bd1ffaf51d1941762dd4b1c21eb54913.jpg",
    "type" : "image/jpeg",
    "bitrate" : 0,
    "duration" : 0,
    "title" : null,
    "properties" : null,
    "alternate" : [ {
      "href" : "https://img.abctruyen.xyz/uploads/9925/chuong-15/1.jpg",
      "type" : "image/jpeg",
      "bitrate" : 0,
      "duration" : 0,
      "title" : null,
      "properties" : null,
      "alternate" : null
    } ]
  }, {
    "href" : "https://bitbucket.org/wp-tsvhcomic11/comic_storage_two15/raw/master/IMAGE/IMAGE_b38a5f72f44377918adb1ed66534f764_a0092bb9390c00ed01ea830059fd4a97_2c60af709e5aaa5db730e767561d58b3.jpg",
    "type" : "image/jpeg",
    "bitrate" : 0,
    "duration" : 0,
    "title" : null,
    "properties" : null,
    "alternate" : [ {
      "href" : "https://img.abctruyen.xyz/uploads/9925/chuong-15/2.jpg",
      "type" : "image/jpeg",
      "bitrate" : 0,
      "duration" : 0,
      "title" : null,
      "properties" : null,
      "alternate" : null
    } ]
  }, {
    "href" : "https://bitbucket.org/wp-tsvhcomic11/comic_storage_two15/raw/master/IMAGE/IMAGE_b38a5f72f44377918adb1ed66534f764_a0092bb9390c00ed01ea830059fd4a97_05661385eeb043a7d022e2c6124186c6.jpg",
    "type" : "image/jpeg",
    "bitrate" : 0,
    "duration" : 0,
    "title" : null,
    "properties" : null,
    "alternate" : [ {
      "href" : "https://img.abctruyen.xyz/uploads/9925/chuong-15/3.jpg",
      "type" : "image/jpeg",
      "bitrate" : 0,
      "duration" : 0,
      "title" : null,
      "properties" : null,
      "alternate" : null
    } ]
  }, {
    "href" : "https://bitbucket.org/wp-tsvhcomic11/comic_storage_two15/raw/master/IMAGE/IMAGE_b38a5f72f44377918adb1ed66534f764_a0092bb9390c00ed01ea830059fd4a97_97206dc164087b741a7435c00f31d822.jpg",
    "type" : "image/jpeg",
    "bitrate" : 0,
    "duration" : 0,
    "title" : null,
    "properties" : null,
    "alternate" : [ {
      "href" : "https://img.abctruyen.xyz/uploads/9925/chuong-15/4.jpg",
      "type" : "image/jpeg",
      "bitrate" : 0,
      "duration" : 0,
      "title" : null,
      "properties" : null,
      "alternate" : null
    } ]
  }, {
    "href" : "https://bitbucket.org/wp-tsvhcomic11/comic_storage_two15/raw/master/IMAGE/IMAGE_b38a5f72f44377918adb1ed66534f764_a0092bb9390c00ed01ea830059fd4a97_a27eaba4a0f6ec41104228f076ba4724.jpg",
    "type" : "image/jpeg",
    "bitrate" : 0,
    "duration" : 0,
    "title" : null,
    "properties" : null,
    "alternate" : [ {
      "href" : "https://img.abctruyen.xyz/uploads/9925/chuong-15/5.jpg",
      "type" : "image/jpeg",
      "bitrate" : 0,
      "duration" : 0,
      "title" : null,
      "properties" : null,
      "alternate" : null
    } ]
  }, {
    "href" : "https://bitbucket.org/wp-tsvhcomic11/comic_storage_two15/raw/master/IMAGE/IMAGE_b38a5f72f44377918adb1ed66534f764_a0092bb9390c00ed01ea830059fd4a97_d9c55beca9007b4bb43cac00d240a214.jpg",
    "type" : "image/jpeg",
    "bitrate" : 0,
    "duration" : 0,
    "title" : null,
    "properties" : null,
    "alternate" : [ {
      "href" : "https://img.abctruyen.xyz/uploads/9925/chuong-15/6.jpg",
      "type" : "image/jpeg",
      "bitrate" : 0,
      "duration" : 0,
      "title" : null,
      "properties" : null,
      "alternate" : null
    } ]
  }, {
    "href" : "https://bitbucket.org/wp-tsvhcomic11/comic_storage_two15/raw/master/IMAGE/IMAGE_b38a5f72f44377918adb1ed66534f764_a0092bb9390c00ed01ea830059fd4a97_268963508d1a7b56678a37c8ebee3929.jpg",
    "type" : "image/jpeg",
    "bitrate" : 0,
    "duration" : 0,
    "title" : null,
    "properties" : null,
    "alternate" : [ {
      "href" : "https://img.abctruyen.xyz/uploads/9925/chuong-15/7.jpg",
      "type" : "image/jpeg",
      "bitrate" : 0,
      "duration" : 0,
      "title" : null,
      "properties" : null,
      "alternate" : null
    } ]
  }, {
    "href" : "https://bitbucket.org/wp-tsvhcomic11/comic_storage_two15/raw/master/IMAGE/IMAGE_b38a5f72f44377918adb1ed66534f764_a0092bb9390c00ed01ea830059fd4a97_80a677327ba7222a37659a0b3b859627.jpg",
    "type" : "image/jpeg",
    "bitrate" : 0,
    "duration" : 0,
    "title" : null,
    "properties" : null,
    "alternate" : [ {
      "href" : "https://img.abctruyen.xyz/uploads/9925/chuong-15/8.jpg",
      "type" : "image/jpeg",
      "bitrate" : 0,
      "duration" : 0,
      "title" : null,
      "properties" : null,
      "alternate" : null
    } ]
  }, {
    "href" : "https://bitbucket.org/wp-tsvhcomic11/comic_storage_two15/raw/master/IMAGE/IMAGE_b38a5f72f44377918adb1ed66534f764_a0092bb9390c00ed01ea830059fd4a97_fdde0606a248bd1819f11b62e5a2ca6d.jpg",
    "type" : "image/jpeg",
    "bitrate" : 0,
    "duration" : 0,
    "title" : null,
    "properties" : null,
    "alternate" : [ {
      "href" : "https://img.abctruyen.xyz/uploads/9925/chuong-15/9.jpg",
      "type" : "image/jpeg",
      "bitrate" : 0,
      "duration" : 0,
      "title" : null,
      "properties" : null,
      "alternate" : null
    } ]
  }, {
    "href" : "https://bitbucket.org/wp-tsvhcomic11/comic_storage_two15/raw/master/IMAGE/IMAGE_b38a5f72f44377918adb1ed66534f764_a0092bb9390c00ed01ea830059fd4a97_fb7e239a9afcc58822843a3175b0f339.jpg",
    "type" : "image/jpeg",
    "bitrate" : 0,
    "duration" : 0,
    "title" : null,
    "properties" : null,
    "alternate" : [ {
      "href" : "https://img.abctruyen.xyz/uploads/9925/chuong-15/10.jpg",
      "type" : "image/jpeg",
      "bitrate" : 0,
      "duration" : 0,
      "title" : null,
      "properties" : null,
      "alternate" : null
    } ]
  }, {
    "href" : "https://bitbucket.org/wp-tsvhcomic11/comic_storage_two15/raw/master/IMAGE/IMAGE_b38a5f72f44377918adb1ed66534f764_a0092bb9390c00ed01ea830059fd4a97_672a5ecdc626e5c86116900370ad1b79.jpg",
    "type" : "image/jpeg",
    "bitrate" : 0,
    "duration" : 0,
    "title" : null,
    "properties" : null,
    "alternate" : [ {
      "href" : "https://img.abctruyen.xyz/uploads/9925/chuong-15/11.jpg",
      "type" : "image/jpeg",
      "bitrate" : 0,
      "duration" : 0,
      "title" : null,
      "properties" : null,
      "alternate" : null
    } ]
  }, {
    "href" : "https://bitbucket.org/wp-tsvhcomic11/comic_storage_two15/raw/master/IMAGE/IMAGE_b38a5f72f44377918adb1ed66534f764_a0092bb9390c00ed01ea830059fd4a97_f0cd73b684747ecfab465d0575401500.jpg",
    "type" : "image/jpeg",
    "bitrate" : 0,
    "duration" : 0,
    "title" : null,
    "properties" : null,
    "alternate" : [ {
      "href" : "https://img.abctruyen.xyz/uploads/9925/chuong-15/12.jpg",
      "type" : "image/jpeg",
      "bitrate" : 0,
      "duration" : 0,
      "title" : null,
      "properties" : null,
      "alternate" : null
    } ]
  }, {
    "href" : "https://bitbucket.org/wp-tsvhcomic11/comic_storage_two15/raw/master/IMAGE/IMAGE_b38a5f72f44377918adb1ed66534f764_a0092bb9390c00ed01ea830059fd4a97_bbe03285194d6f9763586003aaf3ad62.jpg",
    "type" : "image/jpeg",
    "bitrate" : 0,
    "duration" : 0,
    "title" : null,
    "properties" : null,
    "alternate" : [ {
      "href" : "https://img.abctruyen.xyz/uploads/9925/chuong-15/13.jpg",
      "type" : "image/jpeg",
      "bitrate" : 0,
      "duration" : 0,
      "title" : null,
      "properties" : null,
      "alternate" : null
    } ]
  }, {
    "href" : "https://bitbucket.org/wp-tsvhcomic11/comic_storage_two15/raw/master/IMAGE/IMAGE_b38a5f72f44377918adb1ed66534f764_a0092bb9390c00ed01ea830059fd4a97_0a180e48817f6c987a79ffcef5fe3298.jpg",
    "type" : "image/jpeg",
    "bitrate" : 0,
    "duration" : 0,
    "title" : null,
    "properties" : null,
    "alternate" : [ {
      "href" : "https://img.abctruyen.xyz/uploads/9925/chuong-15/14.jpg",
      "type" : "image/jpeg",
      "bitrate" : 0,
      "duration" : 0,
      "title" : null,
      "properties" : null,
      "alternate" : null
    } ]
  }, {
    "href" : "https://bitbucket.org/wp-tsvhcomic11/comic_storage_two15/raw/master/IMAGE/IMAGE_b38a5f72f44377918adb1ed66534f764_a0092bb9390c00ed01ea830059fd4a97_4308478caf9e7c96df4dce115c8fda97.jpg",
    "type" : "image/jpeg",
    "bitrate" : 0,
    "duration" : 0,
    "title" : null,
    "properties" : null,
    "alternate" : [ {
      "href" : "https://img.abctruyen.xyz/uploads/9925/chuong-15/15.jpg",
      "type" : "image/jpeg",
      "bitrate" : 0,
      "duration" : 0,
      "title" : null,
      "properties" : null,
      "alternate" : null
    } ]
  }, {
    "href" : "https://bitbucket.org/wp-tsvhcomic11/comic_storage_two15/raw/master/IMAGE/IMAGE_b38a5f72f44377918adb1ed66534f764_a0092bb9390c00ed01ea830059fd4a97_87ef9264a36a13b0678ec789a195ac19.jpg",
    "type" : "image/jpeg",
    "bitrate" : 0,
    "duration" : 0,
    "title" : null,
    "properties" : null,
    "alternate" : [ {
      "href" : "https://img.abctruyen.xyz/uploads/9925/chuong-15/16.jpg",
      "type" : "image/jpeg",
      "bitrate" : 0,
      "duration" : 0,
      "title" : null,
      "properties" : null,
      "alternate" : null
    } ]
  }, {
    "href" : "https://bitbucket.org/wp-tsvhcomic11/comic_storage_two15/raw/master/IMAGE/IMAGE_b38a5f72f44377918adb1ed66534f764_a0092bb9390c00ed01ea830059fd4a97_2c0a3fb4fc000cb01ccdadd19d60f40f.jpg",
    "type" : "image/jpeg",
    "bitrate" : 0,
    "duration" : 0,
    "title" : null,
    "properties" : null,
    "alternate" : [ {
      "href" : "https://truyenvnhot.net/wp-content/uploads/2022/12/truyenvn-gg-banner.jpg",
      "type" : "image/jpeg",
      "bitrate" : 0,
      "duration" : 0,
      "title" : null,
      "properties" : null,
      "alternate" : null
    }, {
      "href" : "https://i2.wp.com/truyenvnhot.net/wp-content/uploads/2022/12/truyenvn-gg-banner.jpg",
      "type" : "image/jpeg",
      "bitrate" : 0,
      "duration" : 0,
      "title" : null,
      "properties" : null,
      "alternate" : null
    } ]
  } ],
  "toc" : null,
  "@context" : "https://readium.org/webpub-manifest/context.jsonld"
}