{
  "metadata" : {
    "identifier" : "https://www.nettruyento.com/truyen-tranh/dragon-ball-bay-vien-ngoc-rong-35571",
    "title" : "Dragon Ball - Bảy Viên Ngọc Rồng - Chapter 103",
    "subtitle" : null,
    "author" : null,
    "narrator" : null,
    "language" : "vi",
    "description" : null,
    "publisher" : "N/A",
    "subject" : null,
    "modified" : null,
    "published" : "2023-06-09",
    "duration" : 0,
    "abridged" : false,
    "conformsTo" : "https://readium.org/webpub-manifest/profiles/divina",
    "numberOfPages" : 521,
    "readingProgression" : "ttb",
    "belongsTo" : null,
    "presentation" : {
      "fit" : "width",
      "overflow" : "scrolled",
      "continuous" : true
    },
    "@type" : null,
    "schema:license" : null
  },
  "links" : [ {
    "rel" : "self",
    "href" : "https://raw.githubusercontent.com/thuvienonline40/book_storage_collection/main/comic_manifest.json",
    "type" : "application/divina+json"
  } ],
  "readingOrder" : [ {
    "href" : "https://raw.githubusercontent.com/tsvhcomic22/comic_storage2/main/IMAGE/IMAGE_3a95d3f21e1cd0df4fbb86cfbcb58643_d5ba167c8749bb366cd1515602a125a1_5260faa7905a11891a2124b3c9270942.jpg",
    "type" : "image/jpeg",
    "bitrate" : 0,
    "duration" : 0,
    "title" : null,
    "properties" : null,
    "alternate" : [ {
      "href" : "https://i336.ntcdntempv26.com/data/images/3557/44634/001.jpg?data=net",
      "type" : "image/jpeg",
      "bitrate" : 0,
      "duration" : 0,
      "title" : null,
      "properties" : null,
      "alternate" : null
    } ]
  }, {
    "href" : "https://raw.githubusercontent.com/tsvhcomic22/comic_storage2/main/IMAGE/IMAGE_3a95d3f21e1cd0df4fbb86cfbcb58643_d5ba167c8749bb366cd1515602a125a1_9bc5d7a85d12a8b1dd3ddfbd1bf75c3f.jpg",
    "type" : "image/jpeg",
    "bitrate" : 0,
    "duration" : 0,
    "title" : null,
    "properties" : null,
    "alternate" : [ {
      "href" : "https://i336.ntcdntempv26.com/data/images/3557/44634/002.jpg?data=net",
      "type" : "image/jpeg",
      "bitrate" : 0,
      "duration" : 0,
      "title" : null,
      "properties" : null,
      "alternate" : null
    } ]
  }, {
    "href" : "https://raw.githubusercontent.com/tsvhcomic22/comic_storage2/main/IMAGE/IMAGE_3a95d3f21e1cd0df4fbb86cfbcb58643_d5ba167c8749bb366cd1515602a125a1_b3577d7a92bb2be12fa81b9937915fbc.jpg",
    "type" : "image/jpeg",
    "bitrate" : 0,
    "duration" : 0,
    "title" : null,
    "properties" : null,
    "alternate" : [ {
      "href" : "https://i336.ntcdntempv26.com/data/images/3557/44634/003.jpg?data=net",
      "type" : "image/jpeg",
      "bitrate" : 0,
      "duration" : 0,
      "title" : null,
      "properties" : null,
      "alternate" : null
    } ]
  }, {
    "href" : "https://raw.githubusercontent.com/tsvhcomic22/comic_storage2/main/IMAGE/IMAGE_3a95d3f21e1cd0df4fbb86cfbcb58643_d5ba167c8749bb366cd1515602a125a1_0f1e31c47bc4d796f91fde9eea6efaad.jpg",
    "type" : "image/jpeg",
    "bitrate" : 0,
    "duration" : 0,
    "title" : null,
    "properties" : null,
    "alternate" : [ {
      "href" : "https://i336.ntcdntempv26.com/data/images/3557/44634/004.jpg?data=net",
      "type" : "image/jpeg",
      "bitrate" : 0,
      "duration" : 0,
      "title" : null,
      "properties" : null,
      "alternate" : null
    } ]
  }, {
    "href" : "https://raw.githubusercontent.com/tsvhcomic22/comic_storage2/main/IMAGE/IMAGE_3a95d3f21e1cd0df4fbb86cfbcb58643_d5ba167c8749bb366cd1515602a125a1_de63842ab61371e24e03e8f9d64f6671.jpg",
    "type" : "image/jpeg",
    "bitrate" : 0,
    "duration" : 0,
    "title" : null,
    "properties" : null,
    "alternate" : [ {
      "href" : "https://i336.ntcdntempv26.com/data/images/3557/44634/005.jpg?data=net",
      "type" : "image/jpeg",
      "bitrate" : 0,
      "duration" : 0,
      "title" : null,
      "properties" : null,
      "alternate" : null
    } ]
  }, {
    "href" : "https://raw.githubusercontent.com/tsvhcomic22/comic_storage2/main/IMAGE/IMAGE_3a95d3f21e1cd0df4fbb86cfbcb58643_d5ba167c8749bb366cd1515602a125a1_db06f03d14a8c1e2c529fa5e99da6c1c.jpg",
    "type" : "image/jpeg",
    "bitrate" : 0,
    "duration" : 0,
    "title" : null,
    "properties" : null,
    "alternate" : [ {
      "href" : "https://i336.ntcdntempv26.com/data/images/3557/44634/006.jpg?data=net",
      "type" : "image/jpeg",
      "bitrate" : 0,
      "duration" : 0,
      "title" : null,
      "properties" : null,
      "alternate" : null
    } ]
  }, {
    "href" : "https://raw.githubusercontent.com/tsvhcomic22/comic_storage2/main/IMAGE/IMAGE_3a95d3f21e1cd0df4fbb86cfbcb58643_d5ba167c8749bb366cd1515602a125a1_22e5f54569ff2ca13609826c6292f204.jpg",
    "type" : "image/jpeg",
    "bitrate" : 0,
    "duration" : 0,
    "title" : null,
    "properties" : null,
    "alternate" : [ {
      "href" : "https://i336.ntcdntempv26.com/data/images/3557/44634/007.jpg?data=net",
      "type" : "image/jpeg",
      "bitrate" : 0,
      "duration" : 0,
      "title" : null,
      "properties" : null,
      "alternate" : null
    } ]
  }, {
    "href" : "https://raw.githubusercontent.com/tsvhcomic22/comic_storage2/main/IMAGE/IMAGE_3a95d3f21e1cd0df4fbb86cfbcb58643_d5ba167c8749bb366cd1515602a125a1_42162c1de758279e83116a7f54ff38da.jpg",
    "type" : "image/jpeg",
    "bitrate" : 0,
    "duration" : 0,
    "title" : null,
    "properties" : null,
    "alternate" : [ {
      "href" : "https://i336.ntcdntempv26.com/data/images/3557/44634/008.jpg?data=net",
      "type" : "image/jpeg",
      "bitrate" : 0,
      "duration" : 0,
      "title" : null,
      "properties" : null,
      "alternate" : null
    } ]
  }, {
    "href" : "https://raw.githubusercontent.com/tsvhcomic22/comic_storage2/main/IMAGE/IMAGE_3a95d3f21e1cd0df4fbb86cfbcb58643_d5ba167c8749bb366cd1515602a125a1_ebf75848ef8aaa46902d967d1f54ef39.jpg",
    "type" : "image/jpeg",
    "bitrate" : 0,
    "duration" : 0,
    "title" : null,
    "properties" : null,
    "alternate" : [ {
      "href" : "https://i336.ntcdntempv26.com/data/images/3557/44634/009.jpg?data=net",
      "type" : "image/jpeg",
      "bitrate" : 0,
      "duration" : 0,
      "title" : null,
      "properties" : null,
      "alternate" : null
    } ]
  }, {
    "href" : "https://raw.githubusercontent.com/tsvhcomic22/comic_storage2/main/IMAGE/IMAGE_3a95d3f21e1cd0df4fbb86cfbcb58643_d5ba167c8749bb366cd1515602a125a1_7366429cc9e87a2a4eb8d5efa0014006.jpg",
    "type" : "image/jpeg",
    "bitrate" : 0,
    "duration" : 0,
    "title" : null,
    "properties" : null,
    "alternate" : [ {
      "href" : "https://i336.ntcdntempv26.com/data/images/3557/44634/010.jpg?data=net",
      "type" : "image/jpeg",
      "bitrate" : 0,
      "duration" : 0,
      "title" : null,
      "properties" : null,
      "alternate" : null
    } ]
  }, {
    "href" : "https://raw.githubusercontent.com/tsvhcomic22/comic_storage2/main/IMAGE/IMAGE_3a95d3f21e1cd0df4fbb86cfbcb58643_d5ba167c8749bb366cd1515602a125a1_a439716a0bd31dc841da7a51cab84f21.jpg",
    "type" : "image/jpeg",
    "bitrate" : 0,
    "duration" : 0,
    "title" : null,
    "properties" : null,
    "alternate" : [ {
      "href" : "https://i336.ntcdntempv26.com/data/images/3557/44634/011.jpg?data=net",
      "type" : "image/jpeg",
      "bitrate" : 0,
      "duration" : 0,
      "title" : null,
      "properties" : null,
      "alternate" : null
    } ]
  }, {
    "href" : "https://raw.githubusercontent.com/tsvhcomic22/comic_storage2/main/IMAGE/IMAGE_3a95d3f21e1cd0df4fbb86cfbcb58643_d5ba167c8749bb366cd1515602a125a1_74b4289e0bbf51ef95702ba95bdaad48.jpg",
    "type" : "image/jpeg",
    "bitrate" : 0,
    "duration" : 0,
    "title" : null,
    "properties" : null,
    "alternate" : [ {
      "href" : "https://i336.ntcdntempv26.com/data/images/3557/44634/012.jpg?data=net",
      "type" : "image/jpeg",
      "bitrate" : 0,
      "duration" : 0,
      "title" : null,
      "properties" : null,
      "alternate" : null
    } ]
  }, {
    "href" : "https://raw.githubusercontent.com/tsvhcomic22/comic_storage2/main/IMAGE/IMAGE_3a95d3f21e1cd0df4fbb86cfbcb58643_d5ba167c8749bb366cd1515602a125a1_a0491579ad0df5890bbb43010c105bb6.jpg",
    "type" : "image/jpeg",
    "bitrate" : 0,
    "duration" : 0,
    "title" : null,
    "properties" : null,
    "alternate" : [ {
      "href" : "https://i336.ntcdntempv26.com/data/images/3557/44634/013.jpg?data=net",
      "type" : "image/jpeg",
      "bitrate" : 0,
      "duration" : 0,
      "title" : null,
      "properties" : null,
      "alternate" : null
    } ]
  }, {
    "href" : "https://raw.githubusercontent.com/tsvhcomic22/comic_storage2/main/IMAGE/IMAGE_3a95d3f21e1cd0df4fbb86cfbcb58643_d5ba167c8749bb366cd1515602a125a1_c4c1794ca545e8b5a7463de6fb2dcc4a.jpg",
    "type" : "image/jpeg",
    "bitrate" : 0,
    "duration" : 0,
    "title" : null,
    "properties" : null,
    "alternate" : [ {
      "href" : "https://i336.ntcdntempv26.com/data/images/3557/44634/014.jpg?data=net",
      "type" : "image/jpeg",
      "bitrate" : 0,
      "duration" : 0,
      "title" : null,
      "properties" : null,
      "alternate" : null
    } ]
  }, {
    "href" : "https://raw.githubusercontent.com/tsvhcomic22/comic_storage2/main/IMAGE/IMAGE_3a95d3f21e1cd0df4fbb86cfbcb58643_d5ba167c8749bb366cd1515602a125a1_39c96ade492d53998aeb9acb5ba2c6e7.jpg",
    "type" : "image/jpeg",
    "bitrate" : 0,
    "duration" : 0,
    "title" : null,
    "properties" : null,
    "alternate" : [ {
      "href" : "https://i336.ntcdntempv26.com/data/images/3557/44634/015.jpg?data=net",
      "type" : "image/jpeg",
      "bitrate" : 0,
      "duration" : 0,
      "title" : null,
      "properties" : null,
      "alternate" : null
    } ]
  } ],
  "toc" : null,
  "@context" : "https://readium.org/webpub-manifest/context.jsonld"
}