{
  "metadata" : {
    "identifier" : "https://www.nettruyenio.com/truyen-tranh/hapi-mari-24480",
    "title" : "Hapi Mari - Chapter 19",
    "subtitle" : null,
    "author" : null,
    "narrator" : null,
    "language" : "vi",
    "description" : null,
    "publisher" : "N/A",
    "subject" : null,
    "modified" : null,
    "published" : "2023-06-22",
    "duration" : 0,
    "abridged" : false,
    "conformsTo" : "https://readium.org/webpub-manifest/profiles/divina",
    "numberOfPages" : 40,
    "readingProgression" : "ttb",
    "belongsTo" : null,
    "presentation" : {
      "fit" : "width",
      "overflow" : "scrolled",
      "continuous" : true
    },
    "@type" : null,
    "schema:license" : null
  },
  "links" : [ {
    "rel" : "self",
    "href" : "https://raw.githubusercontent.com/thuvienonline40/book_storage_collection/main/comic_manifest.json",
    "type" : "application/divina+json"
  } ],
  "readingOrder" : [ {
    "href" : "https://raw.githubusercontent.com/quetcccd/comic_storage2/main/IMAGE/IMAGE_228b6d5fc241cdabe2da187fc75e34fc_eda15c16372fb23a8e837b79f6cf7d32_2336a92d8681fc142d3aaa60c3bbdc55.jpg",
    "type" : "image/jpeg",
    "bitrate" : 0,
    "duration" : 0,
    "title" : null,
    "properties" : null,
    "alternate" : [ {
      "href" : "https://i336.ntcdntempv26.com/data/images/2448/221316/001.jpg?data=net",
      "type" : "image/jpeg",
      "bitrate" : 0,
      "duration" : 0,
      "title" : null,
      "properties" : null,
      "alternate" : null
    } ]
  }, {
    "href" : "https://raw.githubusercontent.com/quetcccd/comic_storage2/main/IMAGE/IMAGE_228b6d5fc241cdabe2da187fc75e34fc_eda15c16372fb23a8e837b79f6cf7d32_20d88ebee883ad4c8bcecb002c91b5f2.jpg",
    "type" : "image/jpeg",
    "bitrate" : 0,
    "duration" : 0,
    "title" : null,
    "properties" : null,
    "alternate" : [ {
      "href" : "https://i336.ntcdntempv26.com/data/images/2448/221316/002.jpg?data=net",
      "type" : "image/jpeg",
      "bitrate" : 0,
      "duration" : 0,
      "title" : null,
      "properties" : null,
      "alternate" : null
    } ]
  }, {
    "href" : "https://raw.githubusercontent.com/quetcccd/comic_storage2/main/IMAGE/IMAGE_228b6d5fc241cdabe2da187fc75e34fc_eda15c16372fb23a8e837b79f6cf7d32_e17aa710a5fb91834f3c334888c5f7e0.jpg",
    "type" : "image/jpeg",
    "bitrate" : 0,
    "duration" : 0,
    "title" : null,
    "properties" : null,
    "alternate" : [ {
      "href" : "https://i336.ntcdntempv26.com/data/images/2448/221316/003.jpg?data=net",
      "type" : "image/jpeg",
      "bitrate" : 0,
      "duration" : 0,
      "title" : null,
      "properties" : null,
      "alternate" : null
    } ]
  }, {
    "href" : "https://raw.githubusercontent.com/quetcccd/comic_storage2/main/IMAGE/IMAGE_228b6d5fc241cdabe2da187fc75e34fc_eda15c16372fb23a8e837b79f6cf7d32_927f431c0ad8fe321af23d8f2e9b3395.jpg",
    "type" : "image/jpeg",
    "bitrate" : 0,
    "duration" : 0,
    "title" : null,
    "properties" : null,
    "alternate" : [ {
      "href" : "https://i336.ntcdntempv26.com/data/images/2448/221316/004.jpg?data=net",
      "type" : "image/jpeg",
      "bitrate" : 0,
      "duration" : 0,
      "title" : null,
      "properties" : null,
      "alternate" : null
    } ]
  }, {
    "href" : "https://raw.githubusercontent.com/quetcccd/comic_storage2/main/IMAGE/IMAGE_228b6d5fc241cdabe2da187fc75e34fc_eda15c16372fb23a8e837b79f6cf7d32_446d4edd22fd771c5b61c79b9f9bd68e.jpg",
    "type" : "image/jpeg",
    "bitrate" : 0,
    "duration" : 0,
    "title" : null,
    "properties" : null,
    "alternate" : [ {
      "href" : "https://i336.ntcdntempv26.com/data/images/2448/221316/005.jpg?data=net",
      "type" : "image/jpeg",
      "bitrate" : 0,
      "duration" : 0,
      "title" : null,
      "properties" : null,
      "alternate" : null
    } ]
  }, {
    "href" : "https://raw.githubusercontent.com/quetcccd/comic_storage2/main/IMAGE/IMAGE_228b6d5fc241cdabe2da187fc75e34fc_eda15c16372fb23a8e837b79f6cf7d32_99d0a9f5778ef51d63b0f53adf3e945d.jpg",
    "type" : "image/jpeg",
    "bitrate" : 0,
    "duration" : 0,
    "title" : null,
    "properties" : null,
    "alternate" : [ {
      "href" : "https://i336.ntcdntempv26.com/data/images/2448/221316/006.jpg?data=net",
      "type" : "image/jpeg",
      "bitrate" : 0,
      "duration" : 0,
      "title" : null,
      "properties" : null,
      "alternate" : null
    } ]
  }, {
    "href" : "https://raw.githubusercontent.com/quetcccd/comic_storage2/main/IMAGE/IMAGE_228b6d5fc241cdabe2da187fc75e34fc_eda15c16372fb23a8e837b79f6cf7d32_bc3e1ed7408c7f0cf0dbed3bb1f39c2d.jpg",
    "type" : "image/jpeg",
    "bitrate" : 0,
    "duration" : 0,
    "title" : null,
    "properties" : null,
    "alternate" : [ {
      "href" : "https://i336.ntcdntempv26.com/data/images/2448/221316/007.jpg?data=net",
      "type" : "image/jpeg",
      "bitrate" : 0,
      "duration" : 0,
      "title" : null,
      "properties" : null,
      "alternate" : null
    } ]
  }, {
    "href" : "https://raw.githubusercontent.com/quetcccd/comic_storage2/main/IMAGE/IMAGE_228b6d5fc241cdabe2da187fc75e34fc_eda15c16372fb23a8e837b79f6cf7d32_49554ef71f5a0d2d4898394e3706b7b3.jpg",
    "type" : "image/jpeg",
    "bitrate" : 0,
    "duration" : 0,
    "title" : null,
    "properties" : null,
    "alternate" : [ {
      "href" : "https://i336.ntcdntempv26.com/data/images/2448/221316/008.jpg?data=net",
      "type" : "image/jpeg",
      "bitrate" : 0,
      "duration" : 0,
      "title" : null,
      "properties" : null,
      "alternate" : null
    } ]
  }, {
    "href" : "https://raw.githubusercontent.com/quetcccd/comic_storage2/main/IMAGE/IMAGE_228b6d5fc241cdabe2da187fc75e34fc_eda15c16372fb23a8e837b79f6cf7d32_d62779345b90ee56c81797c40aba6ef8.jpg",
    "type" : "image/jpeg",
    "bitrate" : 0,
    "duration" : 0,
    "title" : null,
    "properties" : null,
    "alternate" : [ {
      "href" : "https://i336.ntcdntempv26.com/data/images/2448/221316/009.jpg?data=net",
      "type" : "image/jpeg",
      "bitrate" : 0,
      "duration" : 0,
      "title" : null,
      "properties" : null,
      "alternate" : null
    } ]
  }, {
    "href" : "https://raw.githubusercontent.com/quetcccd/comic_storage2/main/IMAGE/IMAGE_228b6d5fc241cdabe2da187fc75e34fc_eda15c16372fb23a8e837b79f6cf7d32_113a5312d4d371a9bf56e88e2fc6c677.jpg",
    "type" : "image/jpeg",
    "bitrate" : 0,
    "duration" : 0,
    "title" : null,
    "properties" : null,
    "alternate" : [ {
      "href" : "https://i336.ntcdntempv26.com/data/images/2448/221316/010.jpg?data=net",
      "type" : "image/jpeg",
      "bitrate" : 0,
      "duration" : 0,
      "title" : null,
      "properties" : null,
      "alternate" : null
    } ]
  }, {
    "href" : "https://raw.githubusercontent.com/quetcccd/comic_storage2/main/IMAGE/IMAGE_228b6d5fc241cdabe2da187fc75e34fc_eda15c16372fb23a8e837b79f6cf7d32_f3d92bbc1c8d90e03a08ee7d18d5f136.jpg",
    "type" : "image/jpeg",
    "bitrate" : 0,
    "duration" : 0,
    "title" : null,
    "properties" : null,
    "alternate" : [ {
      "href" : "https://i336.ntcdntempv26.com/data/images/2448/221316/011.jpg?data=net",
      "type" : "image/jpeg",
      "bitrate" : 0,
      "duration" : 0,
      "title" : null,
      "properties" : null,
      "alternate" : null
    } ]
  }, {
    "href" : "https://raw.githubusercontent.com/quetcccd/comic_storage2/main/IMAGE/IMAGE_228b6d5fc241cdabe2da187fc75e34fc_eda15c16372fb23a8e837b79f6cf7d32_3071acabbe24b6ab98a95976e50ae714.jpg",
    "type" : "image/jpeg",
    "bitrate" : 0,
    "duration" : 0,
    "title" : null,
    "properties" : null,
    "alternate" : [ {
      "href" : "https://i336.ntcdntempv26.com/data/images/2448/221316/012.jpg?data=net",
      "type" : "image/jpeg",
      "bitrate" : 0,
      "duration" : 0,
      "title" : null,
      "properties" : null,
      "alternate" : null
    } ]
  }, {
    "href" : "https://raw.githubusercontent.com/quetcccd/comic_storage2/main/IMAGE/IMAGE_228b6d5fc241cdabe2da187fc75e34fc_eda15c16372fb23a8e837b79f6cf7d32_6ad46da4574af49f47e25930704a010b.jpg",
    "type" : "image/jpeg",
    "bitrate" : 0,
    "duration" : 0,
    "title" : null,
    "properties" : null,
    "alternate" : [ {
      "href" : "https://i336.ntcdntempv26.com/data/images/2448/221316/013.jpg?data=net",
      "type" : "image/jpeg",
      "bitrate" : 0,
      "duration" : 0,
      "title" : null,
      "properties" : null,
      "alternate" : null
    } ]
  }, {
    "href" : "https://raw.githubusercontent.com/quetcccd/comic_storage2/main/IMAGE/IMAGE_228b6d5fc241cdabe2da187fc75e34fc_eda15c16372fb23a8e837b79f6cf7d32_a1dd2248a0d7488a4df4b0885e43956b.jpg",
    "type" : "image/jpeg",
    "bitrate" : 0,
    "duration" : 0,
    "title" : null,
    "properties" : null,
    "alternate" : [ {
      "href" : "https://i336.ntcdntempv26.com/data/images/2448/221316/014.jpg?data=net",
      "type" : "image/jpeg",
      "bitrate" : 0,
      "duration" : 0,
      "title" : null,
      "properties" : null,
      "alternate" : null
    } ]
  }, {
    "href" : "https://raw.githubusercontent.com/quetcccd/comic_storage2/main/IMAGE/IMAGE_228b6d5fc241cdabe2da187fc75e34fc_eda15c16372fb23a8e837b79f6cf7d32_ec4754973a22c1481bb0dcc387b65c42.jpg",
    "type" : "image/jpeg",
    "bitrate" : 0,
    "duration" : 0,
    "title" : null,
    "properties" : null,
    "alternate" : [ {
      "href" : "https://i336.ntcdntempv26.com/data/images/2448/221316/015.jpg?data=net",
      "type" : "image/jpeg",
      "bitrate" : 0,
      "duration" : 0,
      "title" : null,
      "properties" : null,
      "alternate" : null
    } ]
  }, {
    "href" : "https://raw.githubusercontent.com/quetcccd/comic_storage2/main/IMAGE/IMAGE_228b6d5fc241cdabe2da187fc75e34fc_eda15c16372fb23a8e837b79f6cf7d32_c3e3d0be50a14dc5b797b03207bf20f9.jpg",
    "type" : "image/jpeg",
    "bitrate" : 0,
    "duration" : 0,
    "title" : null,
    "properties" : null,
    "alternate" : [ {
      "href" : "https://i336.ntcdntempv26.com/data/images/2448/221316/016.jpg?data=net",
      "type" : "image/jpeg",
      "bitrate" : 0,
      "duration" : 0,
      "title" : null,
      "properties" : null,
      "alternate" : null
    } ]
  }, {
    "href" : "https://raw.githubusercontent.com/quetcccd/comic_storage2/main/IMAGE/IMAGE_228b6d5fc241cdabe2da187fc75e34fc_eda15c16372fb23a8e837b79f6cf7d32_df896dbfea8d22b5c1f390b1a8e904ff.jpg",
    "type" : "image/jpeg",
    "bitrate" : 0,
    "duration" : 0,
    "title" : null,
    "properties" : null,
    "alternate" : [ {
      "href" : "https://i336.ntcdntempv26.com/data/images/2448/221316/017.jpg?data=net",
      "type" : "image/jpeg",
      "bitrate" : 0,
      "duration" : 0,
      "title" : null,
      "properties" : null,
      "alternate" : null
    } ]
  }, {
    "href" : "https://raw.githubusercontent.com/quetcccd/comic_storage2/main/IMAGE/IMAGE_228b6d5fc241cdabe2da187fc75e34fc_eda15c16372fb23a8e837b79f6cf7d32_a224863ff50879c4130f1de373d76bcc.jpg",
    "type" : "image/jpeg",
    "bitrate" : 0,
    "duration" : 0,
    "title" : null,
    "properties" : null,
    "alternate" : [ {
      "href" : "https://i336.ntcdntempv26.com/data/images/2448/221316/018.jpg?data=net",
      "type" : "image/jpeg",
      "bitrate" : 0,
      "duration" : 0,
      "title" : null,
      "properties" : null,
      "alternate" : null
    } ]
  }, {
    "href" : "https://raw.githubusercontent.com/quetcccd/comic_storage2/main/IMAGE/IMAGE_228b6d5fc241cdabe2da187fc75e34fc_eda15c16372fb23a8e837b79f6cf7d32_9992885a5682f55c68cc92d73be99bb6.jpg",
    "type" : "image/jpeg",
    "bitrate" : 0,
    "duration" : 0,
    "title" : null,
    "properties" : null,
    "alternate" : [ {
      "href" : "https://i336.ntcdntempv26.com/data/images/2448/221316/019.jpg?data=net",
      "type" : "image/jpeg",
      "bitrate" : 0,
      "duration" : 0,
      "title" : null,
      "properties" : null,
      "alternate" : null
    } ]
  }, {
    "href" : "https://raw.githubusercontent.com/quetcccd/comic_storage2/main/IMAGE/IMAGE_228b6d5fc241cdabe2da187fc75e34fc_eda15c16372fb23a8e837b79f6cf7d32_b78593ac5ae4781f4f6a85315b1b3953.jpg",
    "type" : "image/jpeg",
    "bitrate" : 0,
    "duration" : 0,
    "title" : null,
    "properties" : null,
    "alternate" : [ {
      "href" : "https://i336.ntcdntempv26.com/data/images/2448/221316/020.jpg?data=net",
      "type" : "image/jpeg",
      "bitrate" : 0,
      "duration" : 0,
      "title" : null,
      "properties" : null,
      "alternate" : null
    } ]
  }, {
    "href" : "https://raw.githubusercontent.com/quetcccd/comic_storage2/main/IMAGE/IMAGE_228b6d5fc241cdabe2da187fc75e34fc_eda15c16372fb23a8e837b79f6cf7d32_2510f3cae70ad2cb2f7a50147389655d.jpg",
    "type" : "image/jpeg",
    "bitrate" : 0,
    "duration" : 0,
    "title" : null,
    "properties" : null,
    "alternate" : [ {
      "href" : "https://i336.ntcdntempv26.com/data/images/2448/221316/021.jpg?data=net",
      "type" : "image/jpeg",
      "bitrate" : 0,
      "duration" : 0,
      "title" : null,
      "properties" : null,
      "alternate" : null
    } ]
  }, {
    "href" : "https://raw.githubusercontent.com/quetcccd/comic_storage2/main/IMAGE/IMAGE_228b6d5fc241cdabe2da187fc75e34fc_eda15c16372fb23a8e837b79f6cf7d32_7433a1be9320e2f5ab31c8af12a2966d.jpg",
    "type" : "image/jpeg",
    "bitrate" : 0,
    "duration" : 0,
    "title" : null,
    "properties" : null,
    "alternate" : [ {
      "href" : "https://i336.ntcdntempv26.com/data/images/2448/221316/022.jpg?data=net",
      "type" : "image/jpeg",
      "bitrate" : 0,
      "duration" : 0,
      "title" : null,
      "properties" : null,
      "alternate" : null
    } ]
  }, {
    "href" : "https://raw.githubusercontent.com/quetcccd/comic_storage2/main/IMAGE/IMAGE_228b6d5fc241cdabe2da187fc75e34fc_eda15c16372fb23a8e837b79f6cf7d32_d2b9a69abf3dab311767d8e83a93e23b.jpg",
    "type" : "image/jpeg",
    "bitrate" : 0,
    "duration" : 0,
    "title" : null,
    "properties" : null,
    "alternate" : [ {
      "href" : "https://i336.ntcdntempv26.com/data/images/2448/221316/023.jpg?data=net",
      "type" : "image/jpeg",
      "bitrate" : 0,
      "duration" : 0,
      "title" : null,
      "properties" : null,
      "alternate" : null
    } ]
  }, {
    "href" : "https://raw.githubusercontent.com/quetcccd/comic_storage2/main/IMAGE/IMAGE_228b6d5fc241cdabe2da187fc75e34fc_eda15c16372fb23a8e837b79f6cf7d32_e0cc5463b2084c115d6856644aca7b94.jpg",
    "type" : "image/jpeg",
    "bitrate" : 0,
    "duration" : 0,
    "title" : null,
    "properties" : null,
    "alternate" : [ {
      "href" : "https://i336.ntcdntempv26.com/data/images/2448/221316/024.jpg?data=net",
      "type" : "image/jpeg",
      "bitrate" : 0,
      "duration" : 0,
      "title" : null,
      "properties" : null,
      "alternate" : null
    } ]
  }, {
    "href" : "https://raw.githubusercontent.com/quetcccd/comic_storage2/main/IMAGE/IMAGE_228b6d5fc241cdabe2da187fc75e34fc_eda15c16372fb23a8e837b79f6cf7d32_3a3305fd39e68dbb3a2a9d8f612a93f6.jpg",
    "type" : "image/jpeg",
    "bitrate" : 0,
    "duration" : 0,
    "title" : null,
    "properties" : null,
    "alternate" : [ {
      "href" : "https://i336.ntcdntempv26.com/data/images/2448/221316/025.jpg?data=net",
      "type" : "image/jpeg",
      "bitrate" : 0,
      "duration" : 0,
      "title" : null,
      "properties" : null,
      "alternate" : null
    } ]
  }, {
    "href" : "https://raw.githubusercontent.com/quetcccd/comic_storage2/main/IMAGE/IMAGE_228b6d5fc241cdabe2da187fc75e34fc_eda15c16372fb23a8e837b79f6cf7d32_5cadbe2377fc695375428c60b7e10812.jpg",
    "type" : "image/jpeg",
    "bitrate" : 0,
    "duration" : 0,
    "title" : null,
    "properties" : null,
    "alternate" : [ {
      "href" : "https://i336.ntcdntempv26.com/data/images/2448/221316/026.jpg?data=net",
      "type" : "image/jpeg",
      "bitrate" : 0,
      "duration" : 0,
      "title" : null,
      "properties" : null,
      "alternate" : null
    } ]
  }, {
    "href" : "https://raw.githubusercontent.com/quetcccd/comic_storage2/main/IMAGE/IMAGE_228b6d5fc241cdabe2da187fc75e34fc_eda15c16372fb23a8e837b79f6cf7d32_c4a2b427aca83f43fdcb4d4ad6316f77.jpg",
    "type" : "image/jpeg",
    "bitrate" : 0,
    "duration" : 0,
    "title" : null,
    "properties" : null,
    "alternate" : [ {
      "href" : "https://i336.ntcdntempv26.com/data/images/2448/221316/027.jpg?data=net",
      "type" : "image/jpeg",
      "bitrate" : 0,
      "duration" : 0,
      "title" : null,
      "properties" : null,
      "alternate" : null
    } ]
  }, {
    "href" : "https://raw.githubusercontent.com/quetcccd/comic_storage2/main/IMAGE/IMAGE_228b6d5fc241cdabe2da187fc75e34fc_eda15c16372fb23a8e837b79f6cf7d32_0e1b04ecc9851282cefad1af83a3dc9a.jpg",
    "type" : "image/jpeg",
    "bitrate" : 0,
    "duration" : 0,
    "title" : null,
    "properties" : null,
    "alternate" : [ {
      "href" : "https://i336.ntcdntempv26.com/data/images/2448/221316/028.jpg?data=net",
      "type" : "image/jpeg",
      "bitrate" : 0,
      "duration" : 0,
      "title" : null,
      "properties" : null,
      "alternate" : null
    } ]
  }, {
    "href" : "https://raw.githubusercontent.com/quetcccd/comic_storage2/main/IMAGE/IMAGE_228b6d5fc241cdabe2da187fc75e34fc_eda15c16372fb23a8e837b79f6cf7d32_91dd8f081f1eda612e97c5e1800e81fd.jpg",
    "type" : "image/jpeg",
    "bitrate" : 0,
    "duration" : 0,
    "title" : null,
    "properties" : null,
    "alternate" : [ {
      "href" : "https://i336.ntcdntempv26.com/data/images/2448/221316/029.jpg?data=net",
      "type" : "image/jpeg",
      "bitrate" : 0,
      "duration" : 0,
      "title" : null,
      "properties" : null,
      "alternate" : null
    } ]
  }, {
    "href" : "https://raw.githubusercontent.com/quetcccd/comic_storage2/main/IMAGE/IMAGE_228b6d5fc241cdabe2da187fc75e34fc_eda15c16372fb23a8e837b79f6cf7d32_44ae9e49b223b500d5c4bbba237b358e.jpg",
    "type" : "image/jpeg",
    "bitrate" : 0,
    "duration" : 0,
    "title" : null,
    "properties" : null,
    "alternate" : [ {
      "href" : "https://i336.ntcdntempv26.com/data/images/2448/221316/030.jpg?data=net",
      "type" : "image/jpeg",
      "bitrate" : 0,
      "duration" : 0,
      "title" : null,
      "properties" : null,
      "alternate" : null
    } ]
  }, {
    "href" : "https://raw.githubusercontent.com/quetcccd/comic_storage2/main/IMAGE/IMAGE_228b6d5fc241cdabe2da187fc75e34fc_eda15c16372fb23a8e837b79f6cf7d32_49e8088171805a93e71554d55b91efc6.jpg",
    "type" : "image/jpeg",
    "bitrate" : 0,
    "duration" : 0,
    "title" : null,
    "properties" : null,
    "alternate" : [ {
      "href" : "https://i336.ntcdntempv26.com/data/images/2448/221316/031.jpg?data=net",
      "type" : "image/jpeg",
      "bitrate" : 0,
      "duration" : 0,
      "title" : null,
      "properties" : null,
      "alternate" : null
    } ]
  }, {
    "href" : "https://raw.githubusercontent.com/quetcccd/comic_storage2/main/IMAGE/IMAGE_228b6d5fc241cdabe2da187fc75e34fc_eda15c16372fb23a8e837b79f6cf7d32_d4ee0a1b347461f57142f3ccfb2aaa8a.jpg",
    "type" : "image/jpeg",
    "bitrate" : 0,
    "duration" : 0,
    "title" : null,
    "properties" : null,
    "alternate" : [ {
      "href" : "https://i336.ntcdntempv26.com/data/images/2448/221316/032.jpg?data=net",
      "type" : "image/jpeg",
      "bitrate" : 0,
      "duration" : 0,
      "title" : null,
      "properties" : null,
      "alternate" : null
    } ]
  }, {
    "href" : "https://raw.githubusercontent.com/quetcccd/comic_storage2/main/IMAGE/IMAGE_228b6d5fc241cdabe2da187fc75e34fc_eda15c16372fb23a8e837b79f6cf7d32_c48f7f005e2973ce2342fae0e7331850.jpg",
    "type" : "image/jpeg",
    "bitrate" : 0,
    "duration" : 0,
    "title" : null,
    "properties" : null,
    "alternate" : [ {
      "href" : "https://i336.ntcdntempv26.com/data/images/2448/221316/033.jpg?data=net",
      "type" : "image/jpeg",
      "bitrate" : 0,
      "duration" : 0,
      "title" : null,
      "properties" : null,
      "alternate" : null
    } ]
  }, {
    "href" : "https://raw.githubusercontent.com/quetcccd/comic_storage2/main/IMAGE/IMAGE_228b6d5fc241cdabe2da187fc75e34fc_eda15c16372fb23a8e837b79f6cf7d32_a0eb1254483dd6c87fef6ce055cace70.jpg",
    "type" : "image/jpeg",
    "bitrate" : 0,
    "duration" : 0,
    "title" : null,
    "properties" : null,
    "alternate" : [ {
      "href" : "https://i336.ntcdntempv26.com/data/images/2448/221316/034.jpg?data=net",
      "type" : "image/jpeg",
      "bitrate" : 0,
      "duration" : 0,
      "title" : null,
      "properties" : null,
      "alternate" : null
    } ]
  }, {
    "href" : "https://raw.githubusercontent.com/quetcccd/comic_storage2/main/IMAGE/IMAGE_228b6d5fc241cdabe2da187fc75e34fc_eda15c16372fb23a8e837b79f6cf7d32_72ab6b815a22e72dcd17c88245aced4b.jpg",
    "type" : "image/jpeg",
    "bitrate" : 0,
    "duration" : 0,
    "title" : null,
    "properties" : null,
    "alternate" : [ {
      "href" : "https://i336.ntcdntempv26.com/data/images/2448/221316/035.jpg?data=net",
      "type" : "image/jpeg",
      "bitrate" : 0,
      "duration" : 0,
      "title" : null,
      "properties" : null,
      "alternate" : null
    } ]
  }, {
    "href" : "https://raw.githubusercontent.com/quetcccd/comic_storage2/main/IMAGE/IMAGE_228b6d5fc241cdabe2da187fc75e34fc_eda15c16372fb23a8e837b79f6cf7d32_1c3893b6cd83df50d6db96db53fbee76.jpg",
    "type" : "image/jpeg",
    "bitrate" : 0,
    "duration" : 0,
    "title" : null,
    "properties" : null,
    "alternate" : [ {
      "href" : "https://i336.ntcdntempv26.com/data/images/2448/221316/036.jpg?data=net",
      "type" : "image/jpeg",
      "bitrate" : 0,
      "duration" : 0,
      "title" : null,
      "properties" : null,
      "alternate" : null
    } ]
  }, {
    "href" : "https://raw.githubusercontent.com/quetcccd/comic_storage2/main/IMAGE/IMAGE_228b6d5fc241cdabe2da187fc75e34fc_eda15c16372fb23a8e837b79f6cf7d32_5709a046c139e827d35f7bc489a04a69.jpg",
    "type" : "image/jpeg",
    "bitrate" : 0,
    "duration" : 0,
    "title" : null,
    "properties" : null,
    "alternate" : [ {
      "href" : "https://i336.ntcdntempv26.com/data/images/2448/221316/037.jpg?data=net",
      "type" : "image/jpeg",
      "bitrate" : 0,
      "duration" : 0,
      "title" : null,
      "properties" : null,
      "alternate" : null
    } ]
  }, {
    "href" : "https://raw.githubusercontent.com/quetcccd/comic_storage2/main/IMAGE/IMAGE_228b6d5fc241cdabe2da187fc75e34fc_eda15c16372fb23a8e837b79f6cf7d32_5019a23d8978ef3f0341c28fbb5899e6.jpg",
    "type" : "image/jpeg",
    "bitrate" : 0,
    "duration" : 0,
    "title" : null,
    "properties" : null,
    "alternate" : [ {
      "href" : "https://i336.ntcdntempv26.com/data/images/2448/221316/038.jpg?data=net",
      "type" : "image/jpeg",
      "bitrate" : 0,
      "duration" : 0,
      "title" : null,
      "properties" : null,
      "alternate" : null
    } ]
  }, {
    "href" : "https://raw.githubusercontent.com/quetcccd/comic_storage2/main/IMAGE/IMAGE_228b6d5fc241cdabe2da187fc75e34fc_eda15c16372fb23a8e837b79f6cf7d32_6a79cc0fc93a16f6fa6c34445f3d4cfa.jpg",
    "type" : "image/jpeg",
    "bitrate" : 0,
    "duration" : 0,
    "title" : null,
    "properties" : null,
    "alternate" : [ {
      "href" : "https://i336.ntcdntempv26.com/data/images/2448/221316/039.jpg?data=net",
      "type" : "image/jpeg",
      "bitrate" : 0,
      "duration" : 0,
      "title" : null,
      "properties" : null,
      "alternate" : null
    } ]
  }, {
    "href" : "https://raw.githubusercontent.com/quetcccd/comic_storage2/main/IMAGE/IMAGE_228b6d5fc241cdabe2da187fc75e34fc_eda15c16372fb23a8e837b79f6cf7d32_4107f2f590ae7c758d829eb8eec1356d.jpg",
    "type" : "image/jpeg",
    "bitrate" : 0,
    "duration" : 0,
    "title" : null,
    "properties" : null,
    "alternate" : [ {
      "href" : "https://i336.ntcdntempv26.com/data/images/2448/221316/040.jpg?data=net",
      "type" : "image/jpeg",
      "bitrate" : 0,
      "duration" : 0,
      "title" : null,
      "properties" : null,
      "alternate" : null
    } ]
  }, {
    "href" : "https://raw.githubusercontent.com/quetcccd/comic_storage2/main/IMAGE/IMAGE_228b6d5fc241cdabe2da187fc75e34fc_eda15c16372fb23a8e837b79f6cf7d32_8e68f5ec5721f3879b87ebcf1da250ec.jpg",
    "type" : "image/jpeg",
    "bitrate" : 0,
    "duration" : 0,
    "title" : null,
    "properties" : null,
    "alternate" : [ {
      "href" : "https://i336.ntcdntempv26.com/data/images/2448/221316/041.jpg?data=net",
      "type" : "image/jpeg",
      "bitrate" : 0,
      "duration" : 0,
      "title" : null,
      "properties" : null,
      "alternate" : null
    } ]
  }, {
    "href" : "https://raw.githubusercontent.com/quetcccd/comic_storage2/main/IMAGE/IMAGE_228b6d5fc241cdabe2da187fc75e34fc_eda15c16372fb23a8e837b79f6cf7d32_7b96cef6cd9eb35382a3bc7aff0ad05b.jpg",
    "type" : "image/jpeg",
    "bitrate" : 0,
    "duration" : 0,
    "title" : null,
    "properties" : null,
    "alternate" : [ {
      "href" : "https://i336.ntcdntempv26.com/data/images/2448/221316/042.jpg?data=net",
      "type" : "image/jpeg",
      "bitrate" : 0,
      "duration" : 0,
      "title" : null,
      "properties" : null,
      "alternate" : null
    } ]
  }, {
    "href" : "https://raw.githubusercontent.com/quetcccd/comic_storage2/main/IMAGE/IMAGE_228b6d5fc241cdabe2da187fc75e34fc_eda15c16372fb23a8e837b79f6cf7d32_15e2d017a4df2cb253189f8f2cef33fe.jpg",
    "type" : "image/jpeg",
    "bitrate" : 0,
    "duration" : 0,
    "title" : null,
    "properties" : null,
    "alternate" : [ {
      "href" : "https://i336.ntcdntempv26.com/data/images/2448/221316/043.jpg?data=net",
      "type" : "image/jpeg",
      "bitrate" : 0,
      "duration" : 0,
      "title" : null,
      "properties" : null,
      "alternate" : null
    } ]
  }, {
    "href" : "https://raw.githubusercontent.com/quetcccd/comic_storage2/main/IMAGE/IMAGE_228b6d5fc241cdabe2da187fc75e34fc_eda15c16372fb23a8e837b79f6cf7d32_8aa45eca7ec7c0066e8bb5d126469a65.jpg",
    "type" : "image/jpeg",
    "bitrate" : 0,
    "duration" : 0,
    "title" : null,
    "properties" : null,
    "alternate" : [ {
      "href" : "https://i336.ntcdntempv26.com/data/images/2448/221316/044.jpg?data=net",
      "type" : "image/jpeg",
      "bitrate" : 0,
      "duration" : 0,
      "title" : null,
      "properties" : null,
      "alternate" : null
    } ]
  }, {
    "href" : "https://raw.githubusercontent.com/quetcccd/comic_storage2/main/IMAGE/IMAGE_228b6d5fc241cdabe2da187fc75e34fc_eda15c16372fb23a8e837b79f6cf7d32_a4c1ccd41350a2a525f6dcd6d5522e7a.jpg",
    "type" : "image/jpeg",
    "bitrate" : 0,
    "duration" : 0,
    "title" : null,
    "properties" : null,
    "alternate" : [ {
      "href" : "https://i336.ntcdntempv26.com/data/images/2448/221316/045.jpg?data=net",
      "type" : "image/jpeg",
      "bitrate" : 0,
      "duration" : 0,
      "title" : null,
      "properties" : null,
      "alternate" : null
    } ]
  } ],
  "toc" : null,
  "@context" : "https://readium.org/webpub-manifest/context.jsonld"
}