{
  "metadata" : {
    "identifier" : "https://www.nettruyenio.com/truyen-tranh/vung-trom-giau-khong-duoc-430770",
    "title" : "Vụng Trộm Giấu Không Được - Chapter 68.1",
    "subtitle" : null,
    "author" : null,
    "narrator" : null,
    "language" : "vi",
    "description" : null,
    "publisher" : "N/A",
    "subject" : null,
    "modified" : null,
    "published" : "2023-06-22",
    "duration" : 0,
    "abridged" : false,
    "conformsTo" : "https://readium.org/webpub-manifest/profiles/divina",
    "numberOfPages" : 101,
    "readingProgression" : "ttb",
    "belongsTo" : null,
    "presentation" : {
      "fit" : "width",
      "overflow" : "scrolled",
      "continuous" : true
    },
    "@type" : null,
    "schema:license" : null
  },
  "links" : [ {
    "rel" : "self",
    "href" : "https://raw.githubusercontent.com/thuvienonline40/book_storage_collection/main/comic_manifest.json",
    "type" : "application/divina+json"
  } ],
  "readingOrder" : [ {
    "href" : "https://raw.githubusercontent.com/quetcccd/comic_storage2/main/IMAGE/IMAGE_4c432ac22b7957f344ee4fd20ae4d998_fa236a25d1fd822db52d6bd38f8151e1_0d2e13e4db488f5d338d06b4fd7c4b10.jpg",
    "type" : "image/jpeg",
    "bitrate" : 0,
    "duration" : 0,
    "title" : null,
    "properties" : null,
    "alternate" : [ {
      "href" : "https://i226.ntcdntempv26.com/data/images/43077/959865/001-4a2a25a.jpg?data=net",
      "type" : "image/jpeg",
      "bitrate" : 0,
      "duration" : 0,
      "title" : null,
      "properties" : null,
      "alternate" : null
    } ]
  }, {
    "href" : "https://raw.githubusercontent.com/quetcccd/comic_storage2/main/IMAGE/IMAGE_4c432ac22b7957f344ee4fd20ae4d998_fa236a25d1fd822db52d6bd38f8151e1_cba949b2adfde308652ee2cf69298c3a.jpg",
    "type" : "image/jpeg",
    "bitrate" : 0,
    "duration" : 0,
    "title" : null,
    "properties" : null,
    "alternate" : [ {
      "href" : "https://i226.ntcdntempv26.com/data/images/43077/959865/002-b643824.jpg?data=net",
      "type" : "image/jpeg",
      "bitrate" : 0,
      "duration" : 0,
      "title" : null,
      "properties" : null,
      "alternate" : null
    } ]
  }, {
    "href" : "https://raw.githubusercontent.com/quetcccd/comic_storage2/main/IMAGE/IMAGE_4c432ac22b7957f344ee4fd20ae4d998_fa236a25d1fd822db52d6bd38f8151e1_704cd0396d1f81f4e0b48208d580b457.jpg",
    "type" : "image/jpeg",
    "bitrate" : 0,
    "duration" : 0,
    "title" : null,
    "properties" : null,
    "alternate" : [ {
      "href" : "https://i226.ntcdntempv26.com/data/images/43077/959865/003-1e0cb39.jpg?data=net",
      "type" : "image/jpeg",
      "bitrate" : 0,
      "duration" : 0,
      "title" : null,
      "properties" : null,
      "alternate" : null
    } ]
  }, {
    "href" : "https://raw.githubusercontent.com/quetcccd/comic_storage2/main/IMAGE/IMAGE_4c432ac22b7957f344ee4fd20ae4d998_fa236a25d1fd822db52d6bd38f8151e1_4551beec0020eaf9c5437de011a7ff5e.jpg",
    "type" : "image/jpeg",
    "bitrate" : 0,
    "duration" : 0,
    "title" : null,
    "properties" : null,
    "alternate" : [ {
      "href" : "https://i226.ntcdntempv26.com/data/images/43077/959865/004-71bf400.jpg?data=net",
      "type" : "image/jpeg",
      "bitrate" : 0,
      "duration" : 0,
      "title" : null,
      "properties" : null,
      "alternate" : null
    } ]
  }, {
    "href" : "https://raw.githubusercontent.com/quetcccd/comic_storage2/main/IMAGE/IMAGE_4c432ac22b7957f344ee4fd20ae4d998_fa236a25d1fd822db52d6bd38f8151e1_44f5c6fb3888f0a5f7b10a431ef90e28.jpg",
    "type" : "image/jpeg",
    "bitrate" : 0,
    "duration" : 0,
    "title" : null,
    "properties" : null,
    "alternate" : [ {
      "href" : "https://i226.ntcdntempv26.com/data/images/43077/959865/005-6561728.jpg?data=net",
      "type" : "image/jpeg",
      "bitrate" : 0,
      "duration" : 0,
      "title" : null,
      "properties" : null,
      "alternate" : null
    } ]
  }, {
    "href" : "https://raw.githubusercontent.com/quetcccd/comic_storage2/main/IMAGE/IMAGE_4c432ac22b7957f344ee4fd20ae4d998_fa236a25d1fd822db52d6bd38f8151e1_15a2c65d1e3c2597ede5637dff09b5a0.jpg",
    "type" : "image/jpeg",
    "bitrate" : 0,
    "duration" : 0,
    "title" : null,
    "properties" : null,
    "alternate" : [ {
      "href" : "https://i226.ntcdntempv26.com/data/images/43077/959865/006-a499584.jpg?data=net",
      "type" : "image/jpeg",
      "bitrate" : 0,
      "duration" : 0,
      "title" : null,
      "properties" : null,
      "alternate" : null
    } ]
  }, {
    "href" : "https://raw.githubusercontent.com/quetcccd/comic_storage2/main/IMAGE/IMAGE_4c432ac22b7957f344ee4fd20ae4d998_fa236a25d1fd822db52d6bd38f8151e1_3096e2b6f49075fd1932e55f52da3329.jpg",
    "type" : "image/jpeg",
    "bitrate" : 0,
    "duration" : 0,
    "title" : null,
    "properties" : null,
    "alternate" : [ {
      "href" : "https://i226.ntcdntempv26.com/data/images/43077/959865/007-cffc5fe.jpg?data=net",
      "type" : "image/jpeg",
      "bitrate" : 0,
      "duration" : 0,
      "title" : null,
      "properties" : null,
      "alternate" : null
    } ]
  }, {
    "href" : "https://raw.githubusercontent.com/quetcccd/comic_storage2/main/IMAGE/IMAGE_4c432ac22b7957f344ee4fd20ae4d998_fa236a25d1fd822db52d6bd38f8151e1_9a5eafbe4097d20892b737301c0f9b35.jpg",
    "type" : "image/jpeg",
    "bitrate" : 0,
    "duration" : 0,
    "title" : null,
    "properties" : null,
    "alternate" : [ {
      "href" : "https://i226.ntcdntempv26.com/data/images/43077/959865/008-2e47489.jpg?data=net",
      "type" : "image/jpeg",
      "bitrate" : 0,
      "duration" : 0,
      "title" : null,
      "properties" : null,
      "alternate" : null
    } ]
  }, {
    "href" : "https://raw.githubusercontent.com/quetcccd/comic_storage2/main/IMAGE/IMAGE_4c432ac22b7957f344ee4fd20ae4d998_fa236a25d1fd822db52d6bd38f8151e1_7d2c9560e571a84d7dd1032923643aa5.jpg",
    "type" : "image/jpeg",
    "bitrate" : 0,
    "duration" : 0,
    "title" : null,
    "properties" : null,
    "alternate" : [ {
      "href" : "https://i226.ntcdntempv26.com/data/images/43077/959865/009-f95e9d2.jpg?data=net",
      "type" : "image/jpeg",
      "bitrate" : 0,
      "duration" : 0,
      "title" : null,
      "properties" : null,
      "alternate" : null
    } ]
  }, {
    "href" : "https://raw.githubusercontent.com/quetcccd/comic_storage2/main/IMAGE/IMAGE_4c432ac22b7957f344ee4fd20ae4d998_fa236a25d1fd822db52d6bd38f8151e1_a841c7995acc2c9e9d86fae79431cab9.jpg",
    "type" : "image/jpeg",
    "bitrate" : 0,
    "duration" : 0,
    "title" : null,
    "properties" : null,
    "alternate" : [ {
      "href" : "https://i226.ntcdntempv26.com/data/images/43077/959865/010-79a4419.jpg?data=net",
      "type" : "image/jpeg",
      "bitrate" : 0,
      "duration" : 0,
      "title" : null,
      "properties" : null,
      "alternate" : null
    } ]
  }, {
    "href" : "https://raw.githubusercontent.com/quetcccd/comic_storage2/main/IMAGE/IMAGE_4c432ac22b7957f344ee4fd20ae4d998_fa236a25d1fd822db52d6bd38f8151e1_b24f00b073f7af75a59eafab30686a5a.jpg",
    "type" : "image/jpeg",
    "bitrate" : 0,
    "duration" : 0,
    "title" : null,
    "properties" : null,
    "alternate" : [ {
      "href" : "https://i226.ntcdntempv26.com/data/images/43077/959865/011-6704665.jpg?data=net",
      "type" : "image/jpeg",
      "bitrate" : 0,
      "duration" : 0,
      "title" : null,
      "properties" : null,
      "alternate" : null
    } ]
  }, {
    "href" : "https://raw.githubusercontent.com/quetcccd/comic_storage2/main/IMAGE/IMAGE_4c432ac22b7957f344ee4fd20ae4d998_fa236a25d1fd822db52d6bd38f8151e1_e8c7f82e7fde71606cdad3ce40db3f79.jpg",
    "type" : "image/jpeg",
    "bitrate" : 0,
    "duration" : 0,
    "title" : null,
    "properties" : null,
    "alternate" : [ {
      "href" : "https://i226.ntcdntempv26.com/data/images/43077/959865/012-d122d35.jpg?data=net",
      "type" : "image/jpeg",
      "bitrate" : 0,
      "duration" : 0,
      "title" : null,
      "properties" : null,
      "alternate" : null
    } ]
  }, {
    "href" : "https://raw.githubusercontent.com/quetcccd/comic_storage2/main/IMAGE/IMAGE_4c432ac22b7957f344ee4fd20ae4d998_fa236a25d1fd822db52d6bd38f8151e1_94175ef6bb1032b39567fdbd954b3625.jpg",
    "type" : "image/jpeg",
    "bitrate" : 0,
    "duration" : 0,
    "title" : null,
    "properties" : null,
    "alternate" : [ {
      "href" : "https://i226.ntcdntempv26.com/data/images/43077/959865/013-7f075e9.jpg?data=net",
      "type" : "image/jpeg",
      "bitrate" : 0,
      "duration" : 0,
      "title" : null,
      "properties" : null,
      "alternate" : null
    } ]
  }, {
    "href" : "https://raw.githubusercontent.com/quetcccd/comic_storage2/main/IMAGE/IMAGE_4c432ac22b7957f344ee4fd20ae4d998_fa236a25d1fd822db52d6bd38f8151e1_786d944b7fffd1eee10f638e72332fb6.jpg",
    "type" : "image/jpeg",
    "bitrate" : 0,
    "duration" : 0,
    "title" : null,
    "properties" : null,
    "alternate" : [ {
      "href" : "https://i226.ntcdntempv26.com/data/images/43077/959865/014-c37b409.jpg?data=net",
      "type" : "image/jpeg",
      "bitrate" : 0,
      "duration" : 0,
      "title" : null,
      "properties" : null,
      "alternate" : null
    } ]
  }, {
    "href" : "https://raw.githubusercontent.com/quetcccd/comic_storage2/main/IMAGE/IMAGE_4c432ac22b7957f344ee4fd20ae4d998_fa236a25d1fd822db52d6bd38f8151e1_ce03c16a3e9315231f63b6cec204f8f7.jpg",
    "type" : "image/jpeg",
    "bitrate" : 0,
    "duration" : 0,
    "title" : null,
    "properties" : null,
    "alternate" : [ {
      "href" : "https://i226.ntcdntempv26.com/data/images/43077/959865/015-f0866cf.jpg?data=net",
      "type" : "image/jpeg",
      "bitrate" : 0,
      "duration" : 0,
      "title" : null,
      "properties" : null,
      "alternate" : null
    } ]
  }, {
    "href" : "https://raw.githubusercontent.com/quetcccd/comic_storage2/main/IMAGE/IMAGE_4c432ac22b7957f344ee4fd20ae4d998_fa236a25d1fd822db52d6bd38f8151e1_dee6d76e4338f10f3bfe2c0be97b01c5.jpg",
    "type" : "image/jpeg",
    "bitrate" : 0,
    "duration" : 0,
    "title" : null,
    "properties" : null,
    "alternate" : [ {
      "href" : "https://i226.ntcdntempv26.com/data/images/43077/959865/016-e8c2ca6.jpg?data=net",
      "type" : "image/jpeg",
      "bitrate" : 0,
      "duration" : 0,
      "title" : null,
      "properties" : null,
      "alternate" : null
    } ]
  }, {
    "href" : "https://raw.githubusercontent.com/quetcccd/comic_storage2/main/IMAGE/IMAGE_4c432ac22b7957f344ee4fd20ae4d998_fa236a25d1fd822db52d6bd38f8151e1_304def49b5d4b677dca8879569d32543.jpg",
    "type" : "image/jpeg",
    "bitrate" : 0,
    "duration" : 0,
    "title" : null,
    "properties" : null,
    "alternate" : [ {
      "href" : "https://i226.ntcdntempv26.com/data/images/43077/959865/017-ce17f63.jpg?data=net",
      "type" : "image/jpeg",
      "bitrate" : 0,
      "duration" : 0,
      "title" : null,
      "properties" : null,
      "alternate" : null
    } ]
  }, {
    "href" : "https://raw.githubusercontent.com/quetcccd/comic_storage2/main/IMAGE/IMAGE_4c432ac22b7957f344ee4fd20ae4d998_fa236a25d1fd822db52d6bd38f8151e1_487729f6bb125ecf1d8aea320180fcdd.jpg",
    "type" : "image/jpeg",
    "bitrate" : 0,
    "duration" : 0,
    "title" : null,
    "properties" : null,
    "alternate" : [ {
      "href" : "https://i226.ntcdntempv26.com/data/images/43077/959865/018-25f44d8.jpg?data=net",
      "type" : "image/jpeg",
      "bitrate" : 0,
      "duration" : 0,
      "title" : null,
      "properties" : null,
      "alternate" : null
    } ]
  }, {
    "href" : "https://raw.githubusercontent.com/quetcccd/comic_storage2/main/IMAGE/IMAGE_4c432ac22b7957f344ee4fd20ae4d998_fa236a25d1fd822db52d6bd38f8151e1_1549ed5892833cd7cfbd90753bf8d055.jpg",
    "type" : "image/jpeg",
    "bitrate" : 0,
    "duration" : 0,
    "title" : null,
    "properties" : null,
    "alternate" : [ {
      "href" : "https://i226.ntcdntempv26.com/data/images/43077/959865/019-dd37179.jpg?data=net",
      "type" : "image/jpeg",
      "bitrate" : 0,
      "duration" : 0,
      "title" : null,
      "properties" : null,
      "alternate" : null
    } ]
  }, {
    "href" : "https://raw.githubusercontent.com/quetcccd/comic_storage2/main/IMAGE/IMAGE_4c432ac22b7957f344ee4fd20ae4d998_fa236a25d1fd822db52d6bd38f8151e1_63d5bdc312069ffe08455a444281c63f.jpg",
    "type" : "image/jpeg",
    "bitrate" : 0,
    "duration" : 0,
    "title" : null,
    "properties" : null,
    "alternate" : [ {
      "href" : "https://i226.ntcdntempv26.com/data/images/43077/959865/020-6da09c0.jpg?data=net",
      "type" : "image/jpeg",
      "bitrate" : 0,
      "duration" : 0,
      "title" : null,
      "properties" : null,
      "alternate" : null
    } ]
  }, {
    "href" : "https://raw.githubusercontent.com/quetcccd/comic_storage2/main/IMAGE/IMAGE_4c432ac22b7957f344ee4fd20ae4d998_fa236a25d1fd822db52d6bd38f8151e1_a0589a1db2facdef9c103cf5908b8765.jpg",
    "type" : "image/jpeg",
    "bitrate" : 0,
    "duration" : 0,
    "title" : null,
    "properties" : null,
    "alternate" : [ {
      "href" : "https://i226.ntcdntempv26.com/data/images/43077/959865/021-7b77d45.jpg?data=net",
      "type" : "image/jpeg",
      "bitrate" : 0,
      "duration" : 0,
      "title" : null,
      "properties" : null,
      "alternate" : null
    } ]
  }, {
    "href" : "https://raw.githubusercontent.com/quetcccd/comic_storage2/main/IMAGE/IMAGE_4c432ac22b7957f344ee4fd20ae4d998_fa236a25d1fd822db52d6bd38f8151e1_7ffa82d38f61dc062b8c995154ef1190.jpg",
    "type" : "image/jpeg",
    "bitrate" : 0,
    "duration" : 0,
    "title" : null,
    "properties" : null,
    "alternate" : [ {
      "href" : "https://i226.ntcdntempv26.com/data/images/43077/959865/022-a5b1809.jpg?data=net",
      "type" : "image/jpeg",
      "bitrate" : 0,
      "duration" : 0,
      "title" : null,
      "properties" : null,
      "alternate" : null
    } ]
  }, {
    "href" : "https://raw.githubusercontent.com/quetcccd/comic_storage2/main/IMAGE/IMAGE_4c432ac22b7957f344ee4fd20ae4d998_fa236a25d1fd822db52d6bd38f8151e1_de72ec0096dd8c4e348000f545d71e4e.jpg",
    "type" : "image/jpeg",
    "bitrate" : 0,
    "duration" : 0,
    "title" : null,
    "properties" : null,
    "alternate" : [ {
      "href" : "https://i226.ntcdntempv26.com/data/images/43077/959865/023-768adb8.jpg?data=net",
      "type" : "image/jpeg",
      "bitrate" : 0,
      "duration" : 0,
      "title" : null,
      "properties" : null,
      "alternate" : null
    } ]
  }, {
    "href" : "https://raw.githubusercontent.com/quetcccd/comic_storage2/main/IMAGE/IMAGE_4c432ac22b7957f344ee4fd20ae4d998_fa236a25d1fd822db52d6bd38f8151e1_620cd45081ee6d35394b5f2cf799cc98.jpg",
    "type" : "image/jpeg",
    "bitrate" : 0,
    "duration" : 0,
    "title" : null,
    "properties" : null,
    "alternate" : [ {
      "href" : "https://i226.ntcdntempv26.com/data/images/43077/959865/024-162da10.jpg?data=net",
      "type" : "image/jpeg",
      "bitrate" : 0,
      "duration" : 0,
      "title" : null,
      "properties" : null,
      "alternate" : null
    } ]
  }, {
    "href" : "https://raw.githubusercontent.com/quetcccd/comic_storage2/main/IMAGE/IMAGE_4c432ac22b7957f344ee4fd20ae4d998_fa236a25d1fd822db52d6bd38f8151e1_b6fa1e0e6034e1bbdb57f482aa0de8d1.jpg",
    "type" : "image/jpeg",
    "bitrate" : 0,
    "duration" : 0,
    "title" : null,
    "properties" : null,
    "alternate" : [ {
      "href" : "https://i226.ntcdntempv26.com/data/images/43077/959865/025-174a116.jpg?data=net",
      "type" : "image/jpeg",
      "bitrate" : 0,
      "duration" : 0,
      "title" : null,
      "properties" : null,
      "alternate" : null
    } ]
  }, {
    "href" : "https://raw.githubusercontent.com/quetcccd/comic_storage2/main/IMAGE/IMAGE_4c432ac22b7957f344ee4fd20ae4d998_fa236a25d1fd822db52d6bd38f8151e1_5d8a368947489c9d595e5086b0540d14.jpg",
    "type" : "image/jpeg",
    "bitrate" : 0,
    "duration" : 0,
    "title" : null,
    "properties" : null,
    "alternate" : [ {
      "href" : "https://i226.ntcdntempv26.com/data/images/43077/959865/026-f5e88c3.jpg?data=net",
      "type" : "image/jpeg",
      "bitrate" : 0,
      "duration" : 0,
      "title" : null,
      "properties" : null,
      "alternate" : null
    } ]
  }, {
    "href" : "https://raw.githubusercontent.com/quetcccd/comic_storage2/main/IMAGE/IMAGE_4c432ac22b7957f344ee4fd20ae4d998_fa236a25d1fd822db52d6bd38f8151e1_a2815d3977d3d553ad873a84830ffff3.jpg",
    "type" : "image/jpeg",
    "bitrate" : 0,
    "duration" : 0,
    "title" : null,
    "properties" : null,
    "alternate" : [ {
      "href" : "https://i226.ntcdntempv26.com/data/images/43077/959865/027-3d38ef7.jpg?data=net",
      "type" : "image/jpeg",
      "bitrate" : 0,
      "duration" : 0,
      "title" : null,
      "properties" : null,
      "alternate" : null
    } ]
  }, {
    "href" : "https://raw.githubusercontent.com/quetcccd/comic_storage2/main/IMAGE/IMAGE_4c432ac22b7957f344ee4fd20ae4d998_fa236a25d1fd822db52d6bd38f8151e1_5aaf7ff45100561f9b461b30e43cdd5e.jpg",
    "type" : "image/jpeg",
    "bitrate" : 0,
    "duration" : 0,
    "title" : null,
    "properties" : null,
    "alternate" : [ {
      "href" : "https://i226.ntcdntempv26.com/data/images/43077/959865/028-141f78c.jpg?data=net",
      "type" : "image/jpeg",
      "bitrate" : 0,
      "duration" : 0,
      "title" : null,
      "properties" : null,
      "alternate" : null
    } ]
  }, {
    "href" : "https://raw.githubusercontent.com/quetcccd/comic_storage2/main/IMAGE/IMAGE_4c432ac22b7957f344ee4fd20ae4d998_fa236a25d1fd822db52d6bd38f8151e1_4ea97cf830c985052c65829a4a1b1cc1.jpg",
    "type" : "image/jpeg",
    "bitrate" : 0,
    "duration" : 0,
    "title" : null,
    "properties" : null,
    "alternate" : [ {
      "href" : "https://i226.ntcdntempv26.com/data/images/43077/959865/029-e40f522.jpg?data=net",
      "type" : "image/jpeg",
      "bitrate" : 0,
      "duration" : 0,
      "title" : null,
      "properties" : null,
      "alternate" : null
    } ]
  } ],
  "toc" : null,
  "@context" : "https://readium.org/webpub-manifest/context.jsonld"
}